{
  "urls": [
    "/w/womens-trousers-tights-2kq19z5e1x6"
  ],
  "category": "leggings",
  "section": "womens",
  "label": "clothing",
  "multipleUrls": null,
  "brand": "Nike",
  "domain": "https://www.nike.com/gb",
  "extracts": {
    "topLevel": {
      "scrollPage": true,
      "scrollPageWaitTime": 15000,
      "waitForNode": null,
      "delay": 0,
      "productsSelector": {
        "selector": ".product-card .product-card__body"
      },
      "data": {
        "name": {
          "selector": ".product-card__titles",
          "getDataFrom": "text"
        },
        "price": {
          "selector": ".product-price.is--current-price",
          "getDataFrom": "text"
        },
        "nowPrice": {
          "selector": ".product-price.is--current-price",
          "getDataFrom": "text",
          "isConditional": true
        },
        "wasPrice": {
          "selector": ".product-price.is--striked-out",
          "getDataFrom": "text",
          "isConditional": true
        },
        "link": {
          "selector": "a.product-card__img-link-overlay",
          "getDataFrom": "attr: href"
        },
        "image": {
          "selector": ".product-card__hero-image[src]",
          "getDataFrom": "attr: src"
        }
      }
    },
    "details": {
      "data": {
        "images": {
          "selector": "[data-sub-type='image'] picture source[srcset]:first-child",
          "getDataFrom": "attr: srcset"
        },
        "selectedColor": {
          "selector": ".description-preview__color-description.ncss-li",
          "getDataFrom": "text"
        }
      }
    }
  }
}